lampe/__init__.py
lampe/data.py
lampe/masks.py
lampe/nn.py
lampe/plots.py
lampe/utils.py
lampe/diagnostics/__init__.py
lampe/diagnostics/coverage.py
lampe/inference/__init__.py
lampe/inference/amnre.py
lampe/inference/bnre.py
lampe/inference/cnre.py
lampe/inference/dcp.py
lampe/inference/fmpe.py
lampe/inference/mcmc.py
lampe/inference/npe.py
lampe/inference/nre.py
lampe-0.9.0.dist-info/LICENSE
lampe-0.9.0.dist-info/METADATA
lampe-0.9.0.dist-info/WHEEL
lampe-0.9.0.dist-info/top_level.txt
lampe-0.9.0.dist-info/RECORD
