Metadata-Version: 2.1
Name: lampe
Version: 0.9.0
Summary: Likelihood-free AMortized Posterior Estimation with PyTorch
Author-email: The Probabilists <theprobabilists@gmail.com>
Project-URL: documentation, https://lampe.readthedocs.io
Project-URL: source, https://github.com/probabilists/lampe
Project-URL: tracker, https://github.com/probabilists/lampe/issues
Keywords: torch,simulation,inference,amortized,bayesian,posterior,likelihood,mcmc
Classifier: Intended Audience :: Developers
Classifier: Intended Audience :: Science/Research
Classifier: License :: OSI Approved :: MIT License
Classifier: Natural Language :: English
Classifier: Operating System :: OS Independent
Classifier: Programming Language :: Python :: 3
Requires-Python: >=3.8
License-File: LICENSE
Requires-Dist: h5py >=3.0.0
Requires-Dist: matplotlib >=3.6.0
Requires-Dist: numpy >=1.20.0
Requires-Dist: torch >=1.12.0
Requires-Dist: tqdm >=4.52.0
Requires-Dist: zuko >=0.3.0
Provides-Extra: dev
Requires-Dist: pytest ; extra == 'dev'
Requires-Dist: ruff ; extra == 'dev'
